pecan/__init__.py
pecan/configuration.py
pecan/core.py
pecan/decorators.py
pecan/deploy.py
pecan/extensions.py
pecan/hooks.py
pecan/jsonify.py
pecan/log.py
pecan/rest.py
pecan/routing.py
pecan/secure.py
pecan/templating.py
pecan/testing.py
pecan/util.py
pecan/commands/__init__.py
pecan/commands/base.py
pecan/commands/create.py
pecan/commands/serve.py
pecan/commands/shell.py
pecan/compat/__init__.py
pecan/ext/__init__.py
pecan/middleware/__init__.py
pecan/middleware/debug.py
pecan/middleware/errordocument.py
pecan/middleware/recursive.py
pecan/middleware/static.py
pecan/scaffolds/__init__.py
pecan/scaffolds/base/MANIFEST.in
pecan/scaffolds/base/config.py_tmpl
pecan/scaffolds/base/setup.cfg_tmpl
pecan/scaffolds/base/setup.py_tmpl
pecan/scaffolds/base/+package+/__init__.py
pecan/scaffolds/base/+package+/app.py_tmpl
pecan/scaffolds/base/+package+/controllers/__init__.py
pecan/scaffolds/base/+package+/controllers/root.py
pecan/scaffolds/base/+package+/model/__init__.py
pecan/scaffolds/base/+package+/templates/error.html
pecan/scaffolds/base/+package+/templates/index.html
pecan/scaffolds/base/+package+/templates/layout.html
pecan/scaffolds/base/+package+/tests/__init__.py_tmpl
pecan/scaffolds/base/+package+/tests/config.py_tmpl
pecan/scaffolds/base/+package+/tests/test_functional.py_tmpl
pecan/scaffolds/base/+package+/tests/test_units.py
pecan/scaffolds/base/public/css/style.css
pecan/scaffolds/base/public/images/logo.png
pecan/scaffolds/rest-api/config.py_tmpl
pecan/scaffolds/rest-api/setup.cfg_tmpl
pecan/scaffolds/rest-api/setup.py_tmpl
pecan/scaffolds/rest-api/+package+/__init__.py
pecan/scaffolds/rest-api/+package+/app.py_tmpl
pecan/scaffolds/rest-api/+package+/errors.py
pecan/scaffolds/rest-api/+package+/controllers/__init__.py
pecan/scaffolds/rest-api/+package+/controllers/root.py
pecan/scaffolds/rest-api/+package+/model/__init__.py
pecan/scaffolds/rest-api/+package+/tests/__init__.py_tmpl
pecan/scaffolds/rest-api/+package+/tests/config.py_tmpl
pecan-1.5.0.dist-info/AUTHORS
pecan-1.5.0.dist-info/LICENSE
pecan-1.5.0.dist-info/METADATA
pecan-1.5.0.dist-info/WHEEL
pecan-1.5.0.dist-info/entry_points.txt
pecan-1.5.0.dist-info/top_level.txt
pecan-1.5.0.dist-info/RECORD
