Metadata-Version: 2.1
Name: pecan
Version: 1.5.0
Summary: A WSGI object-dispatching web framework, designed to be lean and fast, with few dependencies.
Home-page: http://github.com/pecan/pecan
Author: Jonathan LaCour
Author-email: info@pecanpy.org
License: BSD
Keywords: web framework wsgi object-dispatch http
Classifier: Development Status :: 5 - Production/Stable
Classifier: Environment :: Console
Classifier: Environment :: Web Environment
Classifier: Intended Audience :: Developers
Classifier: Intended Audience :: System Administrators
Classifier: License :: OSI Approved :: BSD License
Classifier: Operating System :: MacOS :: MacOS X
Classifier: Operating System :: Microsoft :: Windows
Classifier: Operating System :: POSIX
Classifier: Programming Language :: Python
Classifier: Programming Language :: Python :: 3
Classifier: Programming Language :: Python :: 3.6
Classifier: Programming Language :: Python :: 3.7
Classifier: Programming Language :: Python :: 3.8
Classifier: Programming Language :: Python :: 3.9
Classifier: Programming Language :: Python :: 3.10
Classifier: Topic :: Internet :: WWW/HTTP :: WSGI
Classifier: Topic :: Software Development :: Libraries :: Application Frameworks
License-File: LICENSE
License-File: AUTHORS
Requires-Dist: WebOb (>=1.8)
Requires-Dist: Mako (>=0.4.0)
Requires-Dist: setuptools
Requires-Dist: logutils (>=0.3)
